mautil/__init__.py
mautil/_version.py
mautil/basic_models.py
mautil/batch_reader.py
mautil/text_process.py
mautil/util.py
mautil/pt/__init__.py
mautil/pt/models.py
mautil/pt/util.py
mautil/tf/__init__.py
mautil/tf/layers.py
mautil/tf/models.py
mautil/tf/optimizer.py
mautil/tf/util.py
mautil/tf/gan/__init__.py
mautil/tf/gan/biggan.py
mautil/tf/gan/gan.py
mautil/tf/nn/__init__.py
mautil/tf/nn/nn.py
mautil/tf/nn/cnn/__init__.py
mautil/tf/nn/cnn/residual.py
mautil/tf/nn/cnn/unet.py
mautil-0.4.6.dist-info/LICENSE
mautil-0.4.6.dist-info/METADATA
mautil-0.4.6.dist-info/WHEEL
mautil-0.4.6.dist-info/top_level.txt
mautil-0.4.6.dist-info/RECORD
